tests/__init__.py
wibe/__init__.py
wibe/__main__.py
wibe-0.0.1.dist-info/METADATA
wibe-0.0.1.dist-info/WHEEL
wibe-0.0.1.dist-info/entry_points.txt
wibe-0.0.1.dist-info/top_level.txt
wibe-0.0.1.dist-info/RECORD
