Metadata-Version: 2.4
Name: wibe
Version: 0.0.1
Summary: WIBE – Wide Input & Bridge for Everything: Read and Write Anything, Anywhere
Home-page: https://github.com/yourusername/wibe
Author: Amarnadh Tirumalasetti
Author-email: amarnadh553@email.com
License: MIT
Classifier: Development Status :: 3 - Alpha
Classifier: Intended Audience :: Developers
Classifier: License :: OSI Approved :: MIT License
Classifier: Programming Language :: Python :: 3
Classifier: Programming Language :: Python :: 3.7
Classifier: Programming Language :: Python :: 3.8
Classifier: Programming Language :: Python :: 3.9
Classifier: Programming Language :: Python :: 3.10
Classifier: Operating System :: OS Independent
Requires-Python: >=3.7
Requires-Dist: PyMuPDF
Requires-Dist: pdfplumber
Requires-Dist: pandas
Requires-Dist: pyyaml
Dynamic: author
Dynamic: author-email
Dynamic: classifier
Dynamic: description
Dynamic: description-content-type
Dynamic: home-page
Dynamic: license
Dynamic: requires-dist
Dynamic: requires-python
Dynamic: summary
